LICENSE
MANIFEST.in
README.md
pyproject.toml
setup.py
unhcrpyplotstyle/__init__.py
unhcrpyplotstyle/unhcrpyplotstyle.mplstyle
unhcrpyplotstyle.egg-info/PKG-INFO
unhcrpyplotstyle.egg-info/SOURCES.txt
unhcrpyplotstyle.egg-info/dependency_links.txt
unhcrpyplotstyle.egg-info/requires.txt
unhcrpyplotstyle.egg-info/top_level.txt
unhcrpyplotstyle/colors/diverging_blue_red.mplstyle
unhcrpyplotstyle/colors/diverging_navy_red.mplstyle
unhcrpyplotstyle/colors/poc.mplstyle
unhcrpyplotstyle/colors/region.mplstyle
unhcrpyplotstyle/colors/sequential_blue.mplstyle
unhcrpyplotstyle/colors/sequential_green.mplstyle
unhcrpyplotstyle/colors/sequential_grey.mplstyle
unhcrpyplotstyle/colors/sequential_navy.mplstyle
unhcrpyplotstyle/colors/sequential_red.mplstyle
unhcrpyplotstyle/colors/sequential_yellow.mplstyle
unhcrpyplotstyle/font/arial.mplstyle
unhcrpyplotstyle/types/area.mplstyle
unhcrpyplotstyle/types/bar.mplstyle
unhcrpyplotstyle/types/bubble.mplstyle
unhcrpyplotstyle/types/column.mplstyle
unhcrpyplotstyle/types/connected_scatterplot.mplstyle
unhcrpyplotstyle/types/donut.mplstyle
unhcrpyplotstyle/types/dotplot.mplstyle
unhcrpyplotstyle/types/heatmap.mplstyle
unhcrpyplotstyle/types/histogram.mplstyle
unhcrpyplotstyle/types/line.mplstyle
unhcrpyplotstyle/types/linecolumn.mplstyle
unhcrpyplotstyle/types/lollipop.mplstyle
unhcrpyplotstyle/types/map.mplstyle
unhcrpyplotstyle/types/pie.mplstyle
unhcrpyplotstyle/types/population_pyramid.mplstyle
unhcrpyplotstyle/types/scatterplot.mplstyle
unhcrpyplotstyle/types/slope.mplstyle
unhcrpyplotstyle/types/streamgraph.mplstyle
unhcrpyplotstyle/types/treemap.mplstyle