Metadata-Version: 2.1
Name: unhcrpyplotstyle
Version: 0.1.3
Summary: Set matplotlib style following UNHCR's Data Visualization Guidelines
Home-page: https://github.com/leichen88/unhcrpyplotstyle
Author: Lei Chen
Author-email: chen@unhcr.org
License: MIT
Keywords: matplotlib-style-sheets,unhcr-plot-style,matplotlib-styles,python
Platform: UNKNOWN
License-File: LICENSE
